mini_trainer/__init__.py
mini_trainer/_version.py
mini_trainer/api_train.py
mini_trainer/async_structured_logger.py
mini_trainer/batch_metrics.py
mini_trainer/batch_packer.py
mini_trainer/fsdp2_lazy_init.py
mini_trainer/gpt_oss_utils.py
mini_trainer/none_reduction_losses.py
mini_trainer/osft_utils.py
mini_trainer/sampler.py
mini_trainer/setup_model_for_training.py
mini_trainer/train.py
mini_trainer/training_types.py
mini_trainer/utils.py
mini_trainer/wandb_wrapper.py
rhai_innovation_mini_trainer-0.5.1.dist-info/licenses/LICENSE.md
rhai_innovation_mini_trainer-0.5.1.dist-info/METADATA
rhai_innovation_mini_trainer-0.5.1.dist-info/WHEEL
rhai_innovation_mini_trainer-0.5.1.dist-info/top_level.txt
rhai_innovation_mini_trainer-0.5.1.dist-info/RECORD
