Metadata-Version: 2.4
Name: rhai-innovation-mini-trainer
Version: 0.5.1
Summary: Simple training repo which is used to house reference implementations of emerging training algorithms, such as Orthogonal Subspace Fine Tuning (OSFT).
Author: Mini Trainer Contributors
License: MIT
Project-URL: Homepage, https://github.com/Red-Hat-AI-Innovation-Team/mini_trainer
Project-URL: Repository, https://github.com/Red-Hat-AI-Innovation-Team/mini_trainer
Project-URL: Issues, https://github.com/Red-Hat-AI-Innovation-Team/mini_trainer/issues
Keywords: machine learning,training,OSFT,orthogonal subspace fine tuning
Classifier: Development Status :: 3 - Alpha
Classifier: Intended Audience :: Developers
Classifier: Intended Audience :: Science/Research
Classifier: License :: OSI Approved :: MIT License
Classifier: Programming Language :: Python :: 3
Classifier: Programming Language :: Python :: 3.11
Classifier: Programming Language :: Python :: 3.12
Classifier: Topic :: Scientific/Engineering :: Artificial Intelligence
Requires-Python: <3.13,>=3.11
License-File: LICENSE.md
Requires-Dist: torch>=2.6
Requires-Dist: typer
Requires-Dist: aiofiles
Requires-Dist: deprecated
Requires-Dist: numpy
Requires-Dist: datasets
Requires-Dist: transformers>=4.55.0
Requires-Dist: ninja
Requires-Dist: numba>=0.62.0
Requires-Dist: rich
Provides-Extra: cuda
Requires-Dist: flash-attn>=2.8.2; extra == "cuda"
Requires-Dist: liger-kernel>=0.5.10; extra == "cuda"
Requires-Dist: kernels; extra == "cuda"
Requires-Dist: mamba-ssm[causal-conv1d]>=2.2.5; extra == "cuda"
Provides-Extra: test
Requires-Dist: pytest>=7.0; extra == "test"
Requires-Dist: pytest-cov; extra == "test"
Requires-Dist: pytest-mock; extra == "test"
Provides-Extra: dev
Requires-Dist: ruff; extra == "dev"
Requires-Dist: ipython; extra == "dev"
Requires-Dist: ipykernel; extra == "dev"
Requires-Dist: ipdb; extra == "dev"
Requires-Dist: pytest; extra == "dev"
Requires-Dist: tox; extra == "dev"
Requires-Dist: tox-uv; extra == "dev"
Provides-Extra: wandb
Requires-Dist: wandb; extra == "wandb"
Dynamic: license-file
